LICENSE
MANIFEST.in
README.md
setup.cfg
setup.py
fastapi_log/__init__.py
fastapi_log/_version.py
fastapi_log/dashboard.py
fastapi_log/log_request.py
fastapi_log.egg-info/PKG-INFO
fastapi_log.egg-info/SOURCES.txt
fastapi_log.egg-info/dependency_links.txt
fastapi_log.egg-info/not-zip-safe
fastapi_log.egg-info/requires.txt
fastapi_log.egg-info/top_level.txt
fastapi_log/database/test.db
fastapi_log/templates/dashboard.html
fastapi_log/templates/index.html
fastapi_log/templates/index_backup.html